odoo/addons/l10n_br_zip/README.rst
odoo/addons/l10n_br_zip/__init__.py
odoo/addons/l10n_br_zip/__manifest__.py
odoo/addons/l10n_br_zip/i18n/es.po
odoo/addons/l10n_br_zip/i18n/l10n_br_zip.pot
odoo/addons/l10n_br_zip/i18n/pt_BR.po
odoo/addons/l10n_br_zip/models/__init__.py
odoo/addons/l10n_br_zip/models/format_address_mixin.py
odoo/addons/l10n_br_zip/models/l10n_br_zip.py
odoo/addons/l10n_br_zip/models/res_config_settings.py
odoo/addons/l10n_br_zip/readme/CONFIGURE.md
odoo/addons/l10n_br_zip/readme/CONTRIBUTORS.md
odoo/addons/l10n_br_zip/readme/DESCRIPTION.md
odoo/addons/l10n_br_zip/readme/HISTORY.md
odoo/addons/l10n_br_zip/readme/INSTALL.md
odoo/addons/l10n_br_zip/readme/ROADMAP.md
odoo/addons/l10n_br_zip/readme/USAGE.md
odoo/addons/l10n_br_zip/security/ir.model.access.csv
odoo/addons/l10n_br_zip/static/description/icon.png
odoo/addons/l10n_br_zip/static/description/index.html
odoo/addons/l10n_br_zip/static/description/l10n_br_zip_1.png
odoo/addons/l10n_br_zip/tests/__init__.py
odoo/addons/l10n_br_zip/tests/test_l10n_br_zip_res_company.py
odoo/addons/l10n_br_zip/tests/test_l10n_br_zip_res_partner.py
odoo/addons/l10n_br_zip/views/l10n_br_zip_view.xml
odoo/addons/l10n_br_zip/views/res_company_views.xml
odoo/addons/l10n_br_zip/views/res_config_settings_view.xml
odoo/addons/l10n_br_zip/views/res_partner_address_view.xml
odoo/addons/l10n_br_zip/wizard/__init__.py
odoo/addons/l10n_br_zip/wizard/l10n_br_zip_search.py
odoo/addons/l10n_br_zip/wizard/l10n_br_zip_search_view.xml
odoo_addon_l10n_br_zip-18.0.1.1.0.1.dist-info/METADATA
odoo_addon_l10n_br_zip-18.0.1.1.0.1.dist-info/WHEEL
odoo_addon_l10n_br_zip-18.0.1.1.0.1.dist-info/top_level.txt
odoo_addon_l10n_br_zip-18.0.1.1.0.1.dist-info/RECORD
